pymarc_csv/__init__.py
pymarc_csv/marccsv.py
pymarc_csv/py.typed
pymarc_csv/reader.py
pymarc_csv/record.py
pymarc_csv/writer.py
pymarc_csv-0.1.1.dist-info/METADATA
pymarc_csv-0.1.1.dist-info/WHEEL
pymarc_csv-0.1.1.dist-info/licenses/LICENSE
pymarc_csv-0.1.1.dist-info/RECORD
