Metadata-Version: 2.4
Name: pymarc_csv
Version: 0.1.1
Summary: CSV reader and writer for MARC records - an extension for pymarc
License: Redistribution and use in source and binary forms, with or without
License-File: LICENSE
Requires-Python: >=3.10
Requires-Dist: pymarc>=5.3.1
